pyexhange.py
modules/price.py
modules/send.py
modules/trade.py
modules/wallet.py
modules/utils/coingecko.py
modules/utils/data.py
modules/utils/exchanges.py
modules/utils/finhub.py
pyexhange_r3ne-0.1.9.dist-info/METADATA
pyexhange_r3ne-0.1.9.dist-info/WHEEL
pyexhange_r3ne-0.1.9.dist-info/licenses/LICENCE.rst
pyexhange_r3ne-0.1.9.dist-info/RECORD
