Metadata-Version: 2.1
Name: pyexhange_r3ne
Version: 0.1.9
Summary: Python code that allows users to create and manage their own virtual wallets to get the trading experiense with out real money.
Project-URL: Homepage, https://github.com/JAAKKQ/pyexhange
Project-URL: Bug Tracker, https://github.com/JAAKKQ/pyexhange/issues
Author-email: "R3ne.net" <mail@r3ne.net>
License-File: LICENCE.rst
Classifier: License :: OSI Approved :: MIT License
Classifier: Operating System :: OS Independent
Classifier: Programming Language :: Python :: 3
Requires-Python: >=3.7
